<?xml version = '1.0' encoding = 'UTF-8'?>
<FKIndexAssociation class="oracle.dbtools.crest.model.design.relational.FKIndexAssociation" directorySegmentName="seg_0" id="27A6B83B-842C-FADA-B2ED-82905F23CF84" containerWithKeyObject="3E383D27-E7DE-D441-C683-72DCFF3C468D" localFKIndex="35FFFB69-EF5A-6909-03AD-4D18E4C1C032" name="TPH_TPL_FK">
<sourceConnName>ATP - SURVEY TOOL</sourceConnName>
<sourceObjSchema>SURVEY_TOOL</sourceObjSchema>
<sourceObjName>TPH_UFE_FK</sourceObjName>
<createdBy>therwix</createdBy>
<createdTime>2021-08-09 10:20:42 UTC</createdTime>
<ownerDesignName>Excel_Gateway</ownerDesignName>
<referredTableLongName>SURVEY_TOOL.R_TEMPLATES</referredTableLongName>
<deleteRule>NO ACTION</deleteRule>
<referredTableID>782288FD-B52D-7ED3-0A67-339F2B46FBDF</referredTableID>
<keyObject>21A65006-357A-0F10-CF13-BCFA739244F5</keyObject>
<referredKeyID>21A65006-357A-0F10-CF13-BCFA739244F5</referredKeyID>
<mandatory>true</mandatory>
<refColNames>TPL_ID</refColNames>
<transferable>true</transferable>
<rely>false</rely>
<columnDependencyConstraintGenerateInDDL>true</columnDependencyConstraintGenerateInDDL>
</FKIndexAssociation>